model_provenance/__init__.py
model_provenance/model_provenance.py
tests/__init__.py
tests/test_model_provenance.py
model_provenance-0.1.1.dist-info/LICENSE
model_provenance-0.1.1.dist-info/METADATA
model_provenance-0.1.1.dist-info/WHEEL
model_provenance-0.1.1.dist-info/top_level.txt
model_provenance-0.1.1.dist-info/RECORD
